{
  "textures": {
    "particle": "bitreplicator:blocks/replicator_top",
    "top": "bitreplicator:blocks/replicator_top",
    "front": "bitreplicator:blocks/replicator_front",
    "inner": "bitreplicator:blocks/replicator_inner"
  },
  "elements": [
    {
      "from": [
        0,
        0,
        0
      ],
      "to": [
        16,
        3,
        16
      ],
      "faces": {
        "down": {
          "uv": [
            0,
            0,
            16,
            16
          ],
          "texture": "#top",
          "cullface": "down"
        },
        "up": {
          "uv": [
            0,
            0,
            16,
            16
          ],
          "texture": "#inner"
        },
        "north": {
          "uv": [
            0,
            13,
            16,
            16
          ],
          "texture": "#front",
          "cullface": "north"
        },
        "south": {
          "uv": [
            0,
            13,
            16,
            16
          ],
          "texture": "#front",
          "cullface": "south"
        },
        "west": {
          "uv": [
            0,
            13,
            16,
            16
          ],
          "texture": "#top",
          "cullface": "west"
        },
        "east": {
          "uv": [
            0,
            13,
            16,
            16
          ],
          "texture": "#top",
          "cullface": "east"
        }
      }
    },
    {
      "from": [
        0,
        13,
        0
      ],
      "to": [
        16,
        16,
        16
      ],
      "faces": {
        "down": {
          "uv": [
            0,
            0,
            16,
            16
          ],
          "texture": "#inner"
        },
        "up": {
          "uv": [
            0,
            0,
            16,
            16
          ],
          "texture": "#top",
          "cullface": "up"
        },
        "north": {
          "uv": [
            0,
            0,
            16,
            3
          ],
          "texture": "#front",
          "cullface": "north"
        },
        "south": {
          "uv": [
            0,
            0,
            16,
            3
          ],
          "texture": "#front",
          "cullface": "south"
        },
        "west": {
          "uv": [
            0,
            0,
            16,
            3
          ],
          "texture": "#top",
          "cullface": "west"
        },
        "east": {
          "uv": [
            0,
            0,
            16,
            3
          ],
          "texture": "#top",
          "cullface": "east"
        }
      }
    },
    {
      "from": [
        2,
        3,
        2
      ],
      "to": [
        14,
        13,
        14
      ],
      "faces": {
        "north": {
          "uv": [
            2,
            3,
            14,
            13
          ],
          "texture": "#front"
        },
        "south": {
          "uv": [
            2,
            3,
            14,
            13
          ],
          "texture": "#front"
        }
      }
    },
    {
      "from": [
        14,
        3,
        0
      ],
      "to": [
        16,
        13,
        16
      ],
      "faces": {
        "north": {
          "uv": [
            0,
            3,
            2,
            13
          ],
          "texture": "#front",
          "cullface": "north"
        },
        "south": {
          "uv": [
            14,
            3,
            16,
            13
          ],
          "texture": "#front",
          "cullface": "south"
        },
        "west": {
          "uv": [
            0,
            3,
            16,
            13
          ],
          "texture": "#inner"
        },
        "east": {
          "uv": [
            0,
            3,
            16,
            13
          ],
          "texture": "#top",
          "cullface": "east"
        }
      }
    },
    {
      "from": [
        0,
        3,
        0
      ],
      "to": [
        2,
        13,
        16
      ],
      "faces": {
        "north": {
          "uv": [
            14,
            3,
            16,
            13
          ],
          "texture": "#front",
          "cullface": "north"
        },
        "south": {
          "uv": [
            0,
            3,
            2,
            13
          ],
          "texture": "#front",
          "cullface": "south"
        },
        "west": {
          "uv": [
            0,
            3,
            16,
            13
          ],
          "texture": "#top",
          "cullface": "west"
        },
        "east": {
          "uv": [
            0,
            3,
            16,
            13
          ],
          "texture": "#inner"
        }
      }
    }
  ],
  "display": {
    "thirdperson_righthand": {
      "rotation": [
        75,
        45,
        0
      ],
      "translation": [
        0,
        2.5,
        0
      ],
      "scale": [
        0.375,
        0.375,
        0.375
      ]
    },
    "thirdperson_lefthand": {
      "rotation": [
        75,
        45,
        0
      ],
      "translation": [
        0,
        2.5,
        0
      ],
      "scale": [
        0.375,
        0.375,
        0.375
      ]
    },
    "firstperson_righthand": {
      "rotation": [
        0,
        45,
        0
      ],
      "scale": [
        0.4,
        0.4,
        0.4
      ]
    },
    "firstperson_lefthand": {
      "rotation": [
        0,
        45,
        0
      ],
      "scale": [
        0.4,
        0.4,
        0.4
      ]
    },
    "gui": {
      "rotation": [
        30,
        225,
        0
      ],
      "scale": [
        0.625,
        0.625,
        0.625
      ]
    },
    "ground": {
      "translation": [
        0,
        3,
        0
      ],
      "scale": [
        0.25,
        0.25,
        0.25
      ]
    },
    "fixed": {
      "scale": [
        0.5,
        0.5,
        0.5
      ]
    }
  }
}